quati/__init__.py
quati_toolkit-1.1.6b0.dist-info/licenses/AUTHORS.md
quati_toolkit-1.1.6b0.dist-info/licenses/LICENSE
quati_toolkit-1.1.6b0.dist-info/METADATA
quati_toolkit-1.1.6b0.dist-info/WHEEL
quati_toolkit-1.1.6b0.dist-info/top_level.txt
quati_toolkit-1.1.6b0.dist-info/RECORD
